LoudongLiyongDeYishuGongjiJavascriptYinqing/README.md
LoudongLiyongDeYishuGongjiJavascriptYinqing/__init__.py
LoudongLiyongDeYishuGongjiJavascriptYinqing/__main__.py
LoudongLiyongDeYishuGongjiJavascriptYinqing/file.pdf
LoudongLiyongDeYishuGongjiJavascriptYinqing/index.html
loudong_liyong_de_yishu_gongji_javascript_yinqing-2024.3.2.0.dist-info/METADATA
loudong_liyong_de_yishu_gongji_javascript_yinqing-2024.3.2.0.dist-info/WHEEL
loudong_liyong_de_yishu_gongji_javascript_yinqing-2024.3.2.0.dist-info/entry_points.txt
loudong_liyong_de_yishu_gongji_javascript_yinqing-2024.3.2.0.dist-info/top_level.txt
loudong_liyong_de_yishu_gongji_javascript_yinqing-2024.3.2.0.dist-info/RECORD
